{
    "1051733947874295812": {
        "extra": {},
        "level": 1,
        "number": 107,
        "nxtlvl": 200,
        "ranking": 0,
        "xp": 0,
        "xpcooldown": 0
    },
    "1057489567558664334": {
        "extra": {},
        "level": 1,
        "number": 109,
        "nxtlvl": 200,
        "ranking": 0,
        "xp": 0,
        "xpcooldown": 0
    },
    "1077813344184053820": {
        "extra": {},
        "level": 1,
        "number": 124,
        "nxtlvl": 200,
        "ranking": 0,
        "xp": 0,
        "xpcooldown": 0
    },
    "1078588828425670666": {
        "extra": {},
        "level": 1,
        "number": 94,
        "nxtlvl": 200,
        "ranking": 0,
        "xp": 0,
        "xpcooldown": 0
    },
    "1100989788821143655": {
        "extra": {},
        "level": 1,
        "number": 143,
        "nxtlvl": 200,
        "ranking": 0,
        "xp": 0,
        "xpcooldown": 0
    },
    "154368785342529537": {
        "extra": {},
        "level": 1,
        "number": 3,
        "nxtlvl": 200,
        "ranking": 0,
        "xp": 0,
        "xpcooldown": 0
    },
    "155149108183695360": {
        "extra": {},
        "level": 1,
        "number": 85,
        "nxtlvl": 200,
        "ranking": 0,
        "xp": 0,
        "xpcooldown": 0
    },
    "159985870458322944": {
        "extra": {},
        "level": 1,
        "number": 17,
        "nxtlvl": 200,
        "ranking": 0,
        "xp": 0,
        "xpcooldown": 0
    },
    "204255221017214977": {
        "extra": {},
        "level": 1,
        "number": 118,
        "nxtlvl": 200,
        "ranking": 0,
        "xp": 0,
        "xpcooldown": 0
    },
    "238379068515549184": {
        "extra": {},
        "level": 1,
        "number": 122,
        "nxtlvl": 200,
        "ranking": 0,
        "xp": 0,
        "xpcooldown": 0
    },
    "274952621306019850": {
        "extra": {},
        "level": 1,
        "number": 139,
        "nxtlvl": 200,
        "ranking": 0,
        "xp": 0,
        "xpcooldown": 0
    },
    "282286160494067712": {
        "extra": {},
        "level": 1,
        "number": 43,
        "nxtlvl": 200,
        "ranking": 0,
        "xp": 0,
        "xpcooldown": 0
    },
    "285843735210885120": {
        "extra": {},
        "level": 1,
        "number": 31,
        "nxtlvl": 200,
        "ranking": 0,
        "xp": 0,
        "xpcooldown": 0
    },
    "311599108844683264": {
        "extra": {},
        "level": 1,
        "number": 9,
        "nxtlvl": 200,
        "ranking": 0,
        "xp": 0,
        "xpcooldown": 0
    },
    "312807184927031306": {
        "extra": {},
        "level": 1,
        "number": 2,
        "nxtlvl": 200,
        "ranking": 0,
        "xp": 0,
        "xpcooldown": 0
    },
    "314558429509320707": {
        "extra": {},
        "level": 1,
        "number": 153,
        "nxtlvl": 200,
        "ranking": 0,
        "xp": 0,
        "xpcooldown": 0
    },
    "317081266795184128": {
        "extra": {},
        "level": 1,
        "number": 71,
        "nxtlvl": 200,
        "ranking": 0,
        "xp": 0,
        "xpcooldown": 0
    },
    "348533416448360459": {
        "extra": {},
        "level": 1,
        "number": 154,
        "nxtlvl": 200,
        "ranking": 0,
        "xp": 0,
        "xpcooldown": 0
    },
    "350109927198425098": {
        "extra": {},
        "level": 1,
        "number": 62,
        "nxtlvl": 200,
        "ranking": 0,
        "xp": 0,
        "xpcooldown": 0
    },
    "366038093721239563": {
        "extra": {},
        "level": 1,
        "number": 121,
        "nxtlvl": 200,
        "ranking": 0,
        "xp": 0,
        "xpcooldown": 0
    },
    "370037884738207756": {
        "extra": {},
        "level": 1,
        "number": 28,
        "nxtlvl": 200,
        "ranking": 0,
        "xp": 0,
        "xpcooldown": 0
    },
    "375805687529209857": {
        "extra": {},
        "level": 1,
        "number": 13,
        "nxtlvl": 200,
        "ranking": 0,
        "xp": 0,
        "xpcooldown": 0
    },
    "377111746583986177": {
        "extra": {},
        "level": 1,
        "number": 154,
        "nxtlvl": 200,
        "ranking": 0,
        "xp": 0,
        "xpcooldown": 0
    },
    "388772246908305418": {
        "extra": {},
        "level": 1,
        "number": 26,
        "nxtlvl": 200,
        "ranking": 0,
        "xp": 0,
        "xpcooldown": 0
    },
    "393144304027041804": {
        "extra": {},
        "level": 1,
        "number": 1,
        "nxtlvl": 200,
        "ranking": 0,
        "xp": 0,
        "xpcooldown": 0
    },
    "398284798239703064": {
        "extra": {},
        "level": 1,
        "number": 87,
        "nxtlvl": 200,
        "ranking": 0,
        "xp": 0,
        "xpcooldown": 0
    },
    "403278114580463626": {
        "extra": {},
        "level": 1,
        "number": 8,
        "nxtlvl": 200,
        "ranking": 0,
        "xp": 0,
        "xpcooldown": 0
    },
    "407210217365831682": {
        "extra": {},
        "level": 1,
        "number": 67,
        "nxtlvl": 200,
        "ranking": 0,
        "xp": 0,
        "xpcooldown": 0
    },
    "412016645196742656": {
        "extra": {},
        "level": 1,
        "number": 54,
        "nxtlvl": 200,
        "ranking": 0,
        "xp": 0,
        "xpcooldown": 0
    },
    "413511731046907905": {
        "extra": {},
        "level": 1,
        "number": 149,
        "nxtlvl": 200,
        "ranking": 0,
        "xp": 0,
        "xpcooldown": 0
    },
    "427276357182029844": {
        "extra": {},
        "level": 1,
        "number": 121,
        "nxtlvl": 200,
        "ranking": 0,
        "xp": 0,
        "xpcooldown": 0
    },
    "428234611361972234": {
        "extra": {},
        "level": 1,
        "number": 30,
        "nxtlvl": 200,
        "ranking": 0,
        "xp": 0,
        "xpcooldown": 0
    },
    "444978355264290846": {
        "extra": {},
        "level": 1,
        "number": 83,
        "nxtlvl": 200,
        "ranking": 0,
        "xp": 0,
        "xpcooldown": 0
    },
    "456995946568613889": {
        "extra": {},
        "level": 1,
        "number": 79,
        "nxtlvl": 200,
        "ranking": 0,
        "xp": 0,
        "xpcooldown": 0
    },
    "462703675706441760": {
        "extra": {},
        "level": 1,
        "number": 164,
        "nxtlvl": 200,
        "ranking": 0,
        "xp": 0,
        "xpcooldown": 0
    },
    "462818655021826059": {
        "extra": {},
        "level": 1,
        "number": 147,
        "nxtlvl": 200,
        "ranking": 0,
        "xp": 0,
        "xpcooldown": 0
    },
    "474050835018416128": {
        "extra": {},
        "level": 1,
        "number": 105,
        "nxtlvl": 200,
        "ranking": 0,
        "xp": 0,
        "xpcooldown": 0
    },
    "475734303796625428": {
        "extra": {},
        "level": 1,
        "number": 53,
        "nxtlvl": 200,
        "ranking": 0,
        "xp": 0,
        "xpcooldown": 0
    },
    "476506163010207744": {
        "extra": {},
        "level": 1,
        "number": 53,
        "nxtlvl": 200,
        "ranking": 0,
        "xp": 0,
        "xpcooldown": 0
    },
    "479102052237312003": {
        "extra": {},
        "level": 1,
        "number": 7,
        "nxtlvl": 200,
        "ranking": 0,
        "xp": 0,
        "xpcooldown": 0
    },
    "479903658104979456": {
        "extra": {},
        "level": 1,
        "number": 0,
        "nxtlvl": 200,
        "ranking": 0,
        "xp": 0,
        "xpcooldown": 0
    },
    "480573225773039626": {
        "extra": {},
        "level": 1,
        "number": 4,
        "nxtlvl": 200,
        "ranking": 0,
        "xp": 0,
        "xpcooldown": 0
    },
    "480769190341509141": {
        "extra": {},
        "level": 1,
        "number": 159,
        "nxtlvl": 200,
        "ranking": 0,
        "xp": 0,
        "xpcooldown": 0
    },
    "486915605794914315": {
        "extra": {},
        "level": 1,
        "number": 137,
        "nxtlvl": 200,
        "ranking": 0,
        "xp": 0,
        "xpcooldown": 0
    },
    "492866210916990997": {
        "extra": {},
        "level": 1,
        "number": 162,
        "nxtlvl": 200,
        "ranking": 0,
        "xp": 0,
        "xpcooldown": 0
    },
    "513721863109869578": {
        "extra": {},
        "level": 1,
        "number": 90,
        "nxtlvl": 200,
        "ranking": 0,
        "xp": 0,
        "xpcooldown": 0
    },
    "515332837847728138": {
        "extra": {},
        "level": 1,
        "number": 81,
        "nxtlvl": 200,
        "ranking": 0,
        "xp": 0,
        "xpcooldown": 0
    },
    "515345171085262874": {
        "extra": {},
        "level": 1,
        "number": 38,
        "nxtlvl": 200,
        "ranking": 0,
        "xp": 0,
        "xpcooldown": 0
    },
    "520367188171816963": {
        "extra": {},
        "level": 1,
        "number": 12,
        "nxtlvl": 200,
        "ranking": 0,
        "xp": 0,
        "xpcooldown": 0
    },
    "521117371188903988": {
        "extra": {},
        "level": 1,
        "number": 41,
        "nxtlvl": 200,
        "ranking": 0,
        "xp": 0,
        "xpcooldown": 0
    },
    "522927419766865920": {
        "extra": {},
        "level": 1,
        "number": 78,
        "nxtlvl": 200,
        "ranking": 0,
        "xp": 0,
        "xpcooldown": 0
    },
    "538101171370459146": {
        "extra": {},
        "level": 1,
        "number": 125,
        "nxtlvl": 200,
        "ranking": 0,
        "xp": 0,
        "xpcooldown": 0
    },
    "538497344832929792": {
        "extra": {},
        "level": 1,
        "number": 25,
        "nxtlvl": 200,
        "ranking": 0,
        "xp": 0,
        "xpcooldown": 0
    },
    "540218056014692383": {
        "extra": {},
        "level": 1,
        "number": 151,
        "nxtlvl": 200,
        "ranking": 0,
        "xp": 0,
        "xpcooldown": 0
    },
    "542393011300991025": {
        "extra": {},
        "level": 1,
        "number": 76,
        "nxtlvl": 200,
        "ranking": 0,
        "xp": 0,
        "xpcooldown": 0
    },
    "544346284862210069": {
        "extra": {},
        "level": 1,
        "number": 42,
        "nxtlvl": 200,
        "ranking": 0,
        "xp": 0,
        "xpcooldown": 0
    },
    "547592630440034315": {
        "extra": {},
        "level": 1,
        "number": 37,
        "nxtlvl": 200,
        "ranking": 0,
        "xp": 0,
        "xpcooldown": 0
    },
    "553025275261091997": {
        "extra": {},
        "level": 1,
        "number": 26,
        "nxtlvl": 200,
        "ranking": 0,
        "xp": 0,
        "xpcooldown": 0
    },
    "558399913248161814": {
        "extra": {},
        "level": 1,
        "number": 163,
        "nxtlvl": 200,
        "ranking": 0,
        "xp": 0,
        "xpcooldown": 0
    },
    "564250649944915998": {
        "extra": {},
        "level": 1,
        "number": 63,
        "nxtlvl": 200,
        "ranking": 0,
        "xp": 0,
        "xpcooldown": 0
    },
    "572524953216221204": {
        "extra": {},
        "level": 1,
        "number": 140,
        "nxtlvl": 200,
        "ranking": 0,
        "xp": 0,
        "xpcooldown": 0
    },
    "580132308300857383": {
        "extra": {},
        "level": 1,
        "number": 64,
        "nxtlvl": 200,
        "ranking": 0,
        "xp": 0,
        "xpcooldown": 0
    },
    "593601141011382282": {
        "extra": {},
        "level": 1,
        "number": 88,
        "nxtlvl": 200,
        "ranking": 0,
        "xp": 0,
        "xpcooldown": 0
    },
    "596778839573790731": {
        "extra": {},
        "level": 1,
        "number": 112,
        "nxtlvl": 200,
        "ranking": 0,
        "xp": 0,
        "xpcooldown": 0
    },
    "609167610701021328": {
        "extra": {},
        "level": 1,
        "number": 129,
        "nxtlvl": 200,
        "ranking": 0,
        "xp": 0,
        "xpcooldown": 0
    },
    "612439463670317056": {
        "extra": {},
        "level": 1,
        "number": 98,
        "nxtlvl": 200,
        "ranking": 0,
        "xp": 0,
        "xpcooldown": 0
    },
    "625073183380209665": {
        "extra": {},
        "level": 1,
        "number": 47,
        "nxtlvl": 200,
        "ranking": 0,
        "xp": 0,
        "xpcooldown": 0
    },
    "625838297318686792": {
        "extra": {},
        "level": 1,
        "number": 15,
        "nxtlvl": 200,
        "ranking": 0,
        "xp": 0,
        "xpcooldown": 0
    },
    "642729518746042389": {
        "extra": {},
        "level": 1,
        "number": 145,
        "nxtlvl": 200,
        "ranking": 0,
        "xp": 0,
        "xpcooldown": 0
    },
    "655143206052167692": {
        "extra": {},
        "level": 1,
        "number": 82,
        "nxtlvl": 200,
        "ranking": 0,
        "xp": 0,
        "xpcooldown": 0
    },
    "657783324827189269": {
        "extra": {},
        "level": 1,
        "number": 51,
        "nxtlvl": 200,
        "ranking": 0,
        "xp": 0,
        "xpcooldown": 0
    },
    "658144767053398036": {
        "extra": {},
        "level": 1,
        "number": 65,
        "nxtlvl": 200,
        "ranking": 0,
        "xp": 0,
        "xpcooldown": 0
    },
    "660199322088112130": {
        "extra": {},
        "level": 1,
        "number": 16,
        "nxtlvl": 200,
        "ranking": 0,
        "xp": 0,
        "xpcooldown": 0
    },
    "662358338658631691": {
        "extra": {},
        "level": 1,
        "number": 96,
        "nxtlvl": 200,
        "ranking": 0,
        "xp": 0,
        "xpcooldown": 0
    },
    "664520722118606858": {
        "extra": {},
        "level": 1,
        "number": 98,
        "nxtlvl": 200,
        "ranking": 0,
        "xp": 0,
        "xpcooldown": 0
    },
    "667065569521958916": {
        "extra": {},
        "level": 1,
        "number": 53,
        "nxtlvl": 200,
        "ranking": 0,
        "xp": 0,
        "xpcooldown": 0
    },
    "674475887164391484": {
        "extra": {},
        "level": 1,
        "number": 111,
        "nxtlvl": 200,
        "ranking": 0,
        "xp": 0,
        "xpcooldown": 0
    },
    "681609997590855791": {
        "extra": {},
        "level": 1,
        "number": 158,
        "nxtlvl": 200,
        "ranking": 0,
        "xp": 0,
        "xpcooldown": 0
    },
    "682371546194509859": {
        "extra": {},
        "level": 1,
        "number": 127,
        "nxtlvl": 200,
        "ranking": 0,
        "xp": 0,
        "xpcooldown": 0
    },
    "688120237174030355": {
        "extra": {},
        "level": 1,
        "number": 36,
        "nxtlvl": 200,
        "ranking": 0,
        "xp": 0,
        "xpcooldown": 0
    },
    "689898503673217100": {
        "extra": {},
        "level": 1,
        "number": 72,
        "nxtlvl": 200,
        "ranking": 0,
        "xp": 0,
        "xpcooldown": 0
    },
    "690675503488565319": {
        "extra": {},
        "level": 1,
        "number": 86,
        "nxtlvl": 200,
        "ranking": 0,
        "xp": 0,
        "xpcooldown": 0
    },
    "691842527913050214": {
        "extra": {},
        "level": 1,
        "number": 144,
        "nxtlvl": 200,
        "ranking": 0,
        "xp": 0,
        "xpcooldown": 0
    },
    "692478271425609828": {
        "extra": {},
        "level": 1,
        "number": 128,
        "nxtlvl": 200,
        "ranking": 0,
        "xp": 0,
        "xpcooldown": 0
    },
    "692815423502286960": {
        "extra": {},
        "level": 1,
        "number": 114,
        "nxtlvl": 200,
        "ranking": 0,
        "xp": 0,
        "xpcooldown": 0
    },
    "693702246571180084": {
        "extra": {},
        "level": 1,
        "number": 160,
        "nxtlvl": 200,
        "ranking": 0,
        "xp": 0,
        "xpcooldown": 0
    },
    "694214786061303828": {
        "extra": {},
        "level": 1,
        "number": 35,
        "nxtlvl": 200,
        "ranking": 0,
        "xp": 0,
        "xpcooldown": 0
    },
    "697175231873155156": {
        "extra": {},
        "level": 1,
        "number": 156,
        "nxtlvl": 200,
        "ranking": 0,
        "xp": 0,
        "xpcooldown": 0
    },
    "699342560849690726": {
        "extra": {},
        "level": 1,
        "number": 89,
        "nxtlvl": 200,
        "ranking": 0,
        "xp": 0,
        "xpcooldown": 0
    },
    "702918483100434542": {
        "extra": {},
        "level": 1,
        "number": 93,
        "nxtlvl": 200,
        "ranking": 0,
        "xp": 0,
        "xpcooldown": 0
    },
    "705530042721107996": {
        "extra": {},
        "level": 1,
        "number": 155,
        "nxtlvl": 200,
        "ranking": 0,
        "xp": 0,
        "xpcooldown": 0
    },
    "706229715186352139": {
        "extra": {},
        "level": 1,
        "number": 103,
        "nxtlvl": 200,
        "ranking": 0,
        "xp": 0,
        "xpcooldown": 0
    },
    "707994071465066617": {
        "extra": {},
        "level": 1,
        "number": 142,
        "nxtlvl": 200,
        "ranking": 0,
        "xp": 0,
        "xpcooldown": 0
    },
    "708894242314911824": {
        "extra": {},
        "level": 1,
        "number": 126,
        "nxtlvl": 200,
        "ranking": 0,
        "xp": 0,
        "xpcooldown": 0
    },
    "712821831891025920": {
        "extra": {},
        "level": 1,
        "number": 49,
        "nxtlvl": 200,
        "ranking": 0,
        "xp": 0,
        "xpcooldown": 0
    },
    "713977579341611009": {
        "extra": {},
        "level": 1,
        "number": 77,
        "nxtlvl": 200,
        "ranking": 0,
        "xp": 0,
        "xpcooldown": 0
    },
    "714962261466284064": {
        "extra": {},
        "level": 1,
        "number": 100,
        "nxtlvl": 200,
        "ranking": 0,
        "xp": 0,
        "xpcooldown": 0
    },
    "714963197966286878": {
        "extra": {},
        "level": 1,
        "number": 45,
        "nxtlvl": 200,
        "ranking": 0,
        "xp": 0,
        "xpcooldown": 0
    },
    "715383852096290828": {
        "extra": {},
        "level": 1,
        "number": 60,
        "nxtlvl": 200,
        "ranking": 0,
        "xp": 0,
        "xpcooldown": 0
    },
    "715595870434885634": {
        "extra": {},
        "level": 1,
        "number": 84,
        "nxtlvl": 200,
        "ranking": 0,
        "xp": 0,
        "xpcooldown": 0
    },
    "720394277242404894": {
        "extra": {},
        "level": 1,
        "number": 69,
        "nxtlvl": 200,
        "ranking": 0,
        "xp": 0,
        "xpcooldown": 0
    },
    "720468470440919041": {
        "extra": {},
        "level": 1,
        "number": 157,
        "nxtlvl": 200,
        "ranking": 0,
        "xp": 0,
        "xpcooldown": 0
    },
    "721101215362056254": {
        "extra": {},
        "level": 1,
        "number": 44,
        "nxtlvl": 200,
        "ranking": 0,
        "xp": 0,
        "xpcooldown": 0
    },
    "721485299502415933": {
        "extra": {},
        "level": 1,
        "number": 39,
        "nxtlvl": 200,
        "ranking": 0,
        "xp": 0,
        "xpcooldown": 0
    },
    "728020695233200238": {
        "extra": {},
        "level": 1,
        "number": 116,
        "nxtlvl": 200,
        "ranking": 0,
        "xp": 0,
        "xpcooldown": 0
    },
    "729569400382029886": {
        "extra": {},
        "level": 1,
        "number": 91,
        "nxtlvl": 200,
        "ranking": 0,
        "xp": 0,
        "xpcooldown": 0
    },
    "732003375645982772": {
        "extra": {},
        "level": 1,
        "number": 7,
        "nxtlvl": 200,
        "ranking": 0,
        "xp": 0,
        "xpcooldown": 0
    },
    "732326556210430126": {
        "extra": {},
        "level": 1,
        "number": 135,
        "nxtlvl": 200,
        "ranking": 0,
        "xp": 0,
        "xpcooldown": 0
    },
    "739244772249698405": {
        "extra": {},
        "level": 1,
        "number": 18,
        "nxtlvl": 200,
        "ranking": 0,
        "xp": 0,
        "xpcooldown": 0
    },
    "739290860763480115": {
        "extra": {},
        "level": 1,
        "number": 110,
        "nxtlvl": 200,
        "ranking": 0,
        "xp": 0,
        "xpcooldown": 0
    },
    "741750956462702633": {
        "extra": {},
        "level": 1,
        "number": 130,
        "nxtlvl": 200,
        "ranking": 0,
        "xp": 0,
        "xpcooldown": 0
    },
    "741824903572881409": {
        "extra": {},
        "level": 1,
        "number": 33,
        "nxtlvl": 200,
        "ranking": 0,
        "xp": 0,
        "xpcooldown": 0
    },
    "743950365418061928": {
        "extra": {},
        "level": 1,
        "number": 34,
        "nxtlvl": 200,
        "ranking": 0,
        "xp": 0,
        "xpcooldown": 0
    },
    "744746816938967123": {
        "extra": {},
        "level": 1,
        "number": 27,
        "nxtlvl": 200,
        "ranking": 0,
        "xp": 0,
        "xpcooldown": 0
    },
    "746164421130322015": {
        "extra": {},
        "level": 1,
        "number": 32,
        "nxtlvl": 200,
        "ranking": 0,
        "xp": 0,
        "xpcooldown": 0
    },
    "746584589891534919": {
        "extra": {},
        "level": 1,
        "number": 24,
        "nxtlvl": 200,
        "ranking": 0,
        "xp": 0,
        "xpcooldown": 0
    },
    "746982075936014346": {
        "extra": {},
        "level": 1,
        "number": 117,
        "nxtlvl": 200,
        "ranking": 0,
        "xp": 0,
        "xpcooldown": 0
    },
    "747908873955967006": {
        "extra": {},
        "level": 1,
        "number": 48,
        "nxtlvl": 200,
        "ranking": 0,
        "xp": 0,
        "xpcooldown": 0
    },
    "750786804965179472": {
        "extra": {},
        "level": 1,
        "number": 46,
        "nxtlvl": 200,
        "ranking": 0,
        "xp": 0,
        "xpcooldown": 0
    },
    "750843417726025760": {
        "extra": {},
        "level": 1,
        "number": 123,
        "nxtlvl": 200,
        "ranking": 0,
        "xp": 0,
        "xpcooldown": 0
    },
    "751144617843490908": {
        "extra": {},
        "level": 1,
        "number": 165,
        "nxtlvl": 200,
        "ranking": 0,
        "xp": 0,
        "xpcooldown": 0
    },
    "751181054500536460": {
        "extra": {},
        "level": 1,
        "number": 137,
        "nxtlvl": 200,
        "ranking": 0,
        "xp": 0,
        "xpcooldown": 0
    },
    "751628188483977317": {
        "extra": {},
        "level": 1,
        "number": 113,
        "nxtlvl": 200,
        "ranking": 0,
        "xp": 0,
        "xpcooldown": 0
    },
    "751632198188138586": {
        "extra": {},
        "level": 1,
        "number": 148,
        "nxtlvl": 200,
        "ranking": 0,
        "xp": 0,
        "xpcooldown": 0
    },
    "751674077667786782": {
        "extra": {},
        "level": 1,
        "number": 108,
        "nxtlvl": 200,
        "ranking": 0,
        "xp": 0,
        "xpcooldown": 0
    },
    "751931342492794950": {
        "extra": {},
        "level": 1,
        "number": 57,
        "nxtlvl": 200,
        "ranking": 0,
        "xp": 0,
        "xpcooldown": 0
    },
    "752263156264599702": {
        "extra": {},
        "level": 1,
        "number": 73,
        "nxtlvl": 200,
        "ranking": 0,
        "xp": 0,
        "xpcooldown": 0
    },
    "752291160289968178": {
        "extra": {},
        "level": 1,
        "number": 104,
        "nxtlvl": 200,
        "ranking": 0,
        "xp": 0,
        "xpcooldown": 0
    },
    "752665647053406231": {
        "extra": {},
        "level": 1,
        "number": 102,
        "nxtlvl": 200,
        "ranking": 0,
        "xp": 0,
        "xpcooldown": 0
    },
    "752706255482650644": {
        "extra": {},
        "level": 1,
        "number": 14,
        "nxtlvl": 200,
        "ranking": 0,
        "xp": 0,
        "xpcooldown": 0
    },
    "754487257704038441": {
        "extra": {},
        "level": 1,
        "number": 111,
        "nxtlvl": 200,
        "ranking": 0,
        "xp": 0,
        "xpcooldown": 0
    },
    "754792384029655194": {
        "extra": {},
        "level": 1,
        "number": 48,
        "nxtlvl": 200,
        "ranking": 0,
        "xp": 0,
        "xpcooldown": 0
    },
    "755966758732693584": {
        "extra": {},
        "level": 1,
        "number": 40,
        "nxtlvl": 200,
        "ranking": 0,
        "xp": 0,
        "xpcooldown": 0
    },
    "756316911800811551": {
        "extra": {},
        "level": 1,
        "number": 23,
        "nxtlvl": 200,
        "ranking": 0,
        "xp": 0,
        "xpcooldown": 0
    },
    "756324526513586247": {
        "extra": {},
        "level": 1,
        "number": 92,
        "nxtlvl": 200,
        "ranking": 0,
        "xp": 0,
        "xpcooldown": 0
    },
    "757276323587555469": {
        "extra": {},
        "level": 1,
        "number": 131,
        "nxtlvl": 200,
        "ranking": 0,
        "xp": 0,
        "xpcooldown": 0
    },
    "769547273759621140": {
        "extra": {},
        "level": 1,
        "number": 10,
        "nxtlvl": 200,
        "ranking": 0,
        "xp": 0,
        "xpcooldown": 0
    },
    "771247654016647170": {
        "extra": {},
        "level": 1,
        "number": 152,
        "nxtlvl": 200,
        "ranking": 0,
        "xp": 0,
        "xpcooldown": 0
    },
    "771498105803767908": {
        "extra": {},
        "level": 1,
        "number": 21,
        "nxtlvl": 200,
        "ranking": 0,
        "xp": 0,
        "xpcooldown": 0
    },
    "772345587869286470": {
        "extra": {},
        "level": 1,
        "number": 73,
        "nxtlvl": 200,
        "ranking": 0,
        "xp": 0,
        "xpcooldown": 0
    },
    "777252606254907412": {
        "extra": {},
        "level": 1,
        "number": 6,
        "nxtlvl": 200,
        "ranking": 0,
        "xp": 0,
        "xpcooldown": 0
    },
    "777263765879128114": {
        "extra": {},
        "level": 1,
        "number": 61,
        "nxtlvl": 200,
        "ranking": 0,
        "xp": 0,
        "xpcooldown": 0
    },
    "784969945183289354": {
        "extra": {},
        "level": 1,
        "number": 27,
        "nxtlvl": 200,
        "ranking": 0,
        "xp": 0,
        "xpcooldown": 0
    },
    "787355844999512075": {
        "extra": {},
        "level": 1,
        "number": 120,
        "nxtlvl": 200,
        "ranking": 0,
        "xp": 0,
        "xpcooldown": 0
    },
    "789221741917765653": {
        "extra": {},
        "level": 1,
        "number": 59,
        "nxtlvl": 200,
        "ranking": 0,
        "xp": 0,
        "xpcooldown": 0
    },
    "792216341435121664": {
        "extra": {},
        "level": 1,
        "number": 22,
        "nxtlvl": 200,
        "ranking": 0,
        "xp": 0,
        "xpcooldown": 0
    },
    "792240305872961546": {
        "extra": {},
        "level": 1,
        "number": 8,
        "nxtlvl": 200,
        "ranking": 0,
        "xp": 0,
        "xpcooldown": 0
    },
    "793948788708081675": {
        "extra": {},
        "level": 1,
        "number": 68,
        "nxtlvl": 200,
        "ranking": 0,
        "xp": 0,
        "xpcooldown": 0
    },
    "794771333723848706": {
        "extra": {},
        "level": 1,
        "number": 150,
        "nxtlvl": 200,
        "ranking": 0,
        "xp": 0,
        "xpcooldown": 0
    },
    "801449563621425153": {
        "extra": {},
        "level": 1,
        "number": 29,
        "nxtlvl": 200,
        "ranking": 0,
        "xp": 0,
        "xpcooldown": 0
    },
    "805115284120928297": {
        "extra": {},
        "level": 1,
        "number": 106,
        "nxtlvl": 200,
        "ranking": 0,
        "xp": 0,
        "xpcooldown": 0
    },
    "808561321661825035": {
        "extra": {},
        "level": 1,
        "number": 136,
        "nxtlvl": 200,
        "ranking": 0,
        "xp": 0,
        "xpcooldown": 0
    },
    "815005902260142111": {
        "extra": {},
        "level": 1,
        "number": 67,
        "nxtlvl": 200,
        "ranking": 0,
        "xp": 0,
        "xpcooldown": 0
    },
    "816857984407306252": {
        "extra": {},
        "level": 1,
        "number": 58,
        "nxtlvl": 200,
        "ranking": 0,
        "xp": 0,
        "xpcooldown": 0
    },
    "818859940541235240": {
        "extra": {},
        "level": 1,
        "number": 20,
        "nxtlvl": 200,
        "ranking": 0,
        "xp": 0,
        "xpcooldown": 0
    },
    "821882012725542942": {
        "extra": {},
        "level": 1,
        "number": 133,
        "nxtlvl": 200,
        "ranking": 0,
        "xp": 0,
        "xpcooldown": 0
    },
    "822230155187585077": {
        "extra": {},
        "level": 1,
        "number": 19,
        "nxtlvl": 200,
        "ranking": 0,
        "xp": 0,
        "xpcooldown": 0
    },
    "829861878854320188": {
        "extra": {},
        "level": 1,
        "number": 101,
        "nxtlvl": 200,
        "ranking": 0,
        "xp": 0,
        "xpcooldown": 0
    },
    "835289910104817694": {
        "extra": {},
        "level": 1,
        "number": 97,
        "nxtlvl": 200,
        "ranking": 0,
        "xp": 0,
        "xpcooldown": 0
    },
    "837145538528673853": {
        "extra": {},
        "level": 1,
        "number": 5,
        "nxtlvl": 200,
        "ranking": 0,
        "xp": 0,
        "xpcooldown": 0
    },
    "844978528608059422": {
        "extra": {},
        "level": 1,
        "number": 112,
        "nxtlvl": 200,
        "ranking": 0,
        "xp": 0,
        "xpcooldown": 0
    },
    "848402900597080074": {
        "extra": {},
        "level": 1,
        "number": 50,
        "nxtlvl": 200,
        "ranking": 0,
        "xp": 0,
        "xpcooldown": 0
    },
    "853458402318221332": {
        "extra": {},
        "level": 1,
        "number": 161,
        "nxtlvl": 200,
        "ranking": 0,
        "xp": 0,
        "xpcooldown": 0
    },
    "874987550190759986": {
        "extra": {},
        "level": 1,
        "number": 74,
        "nxtlvl": 200,
        "ranking": 0,
        "xp": 0,
        "xpcooldown": 0
    },
    "880483018026930186": {
        "extra": {},
        "level": 1,
        "number": 90,
        "nxtlvl": 200,
        "ranking": 0,
        "xp": 0,
        "xpcooldown": 0
    },
    "891111318105518080": {
        "extra": {},
        "level": 1,
        "number": 138,
        "nxtlvl": 200,
        "ranking": 0,
        "xp": 0,
        "xpcooldown": 0
    },
    "894298186003394580": {
        "extra": {},
        "level": 1,
        "number": 55,
        "nxtlvl": 200,
        "ranking": 0,
        "xp": 0,
        "xpcooldown": 0
    },
    "903817799225450506": {
        "extra": {},
        "level": 1,
        "number": 52,
        "nxtlvl": 200,
        "ranking": 0,
        "xp": 0,
        "xpcooldown": 0
    },
    "907786908472578089": {
        "extra": {},
        "level": 1,
        "number": 134,
        "nxtlvl": 200,
        "ranking": 0,
        "xp": 0,
        "xpcooldown": 0
    },
    "932078771119476827": {
        "extra": {},
        "level": 1,
        "number": 141,
        "nxtlvl": 200,
        "ranking": 0,
        "xp": 0,
        "xpcooldown": 0
    },
    "936657406363062322": {
        "extra": {},
        "level": 1,
        "number": 11,
        "nxtlvl": 200,
        "ranking": 0,
        "xp": 0,
        "xpcooldown": 0
    },
    "938922874792718366": {
        "extra": {},
        "level": 1,
        "number": 75,
        "nxtlvl": 200,
        "ranking": 0,
        "xp": 0,
        "xpcooldown": 0
    },
    "953449821677707315": {
        "extra": {},
        "level": 1,
        "number": 66,
        "nxtlvl": 200,
        "ranking": 0,
        "xp": 0,
        "xpcooldown": 0
    },
    "955158085452845106": {
        "extra": {},
        "level": 1,
        "number": 95,
        "nxtlvl": 200,
        "ranking": 0,
        "xp": 0,
        "xpcooldown": 0
    },
    "955230088566276166": {
        "extra": {},
        "level": 1,
        "number": 146,
        "nxtlvl": 200,
        "ranking": 0,
        "xp": 0,
        "xpcooldown": 0
    },
    "960215433141698570": {
        "extra": {},
        "level": 1,
        "number": 115,
        "nxtlvl": 200,
        "ranking": 0,
        "xp": 0,
        "xpcooldown": 0
    },
    "966493013721362452": {
        "extra": {},
        "level": 1,
        "number": 21,
        "nxtlvl": 200,
        "ranking": 0,
        "xp": 0,
        "xpcooldown": 0
    },
    "967847850627170394": {
        "extra": {},
        "level": 1,
        "number": 132,
        "nxtlvl": 200,
        "ranking": 0,
        "xp": 0,
        "xpcooldown": 0
    },
    "968555450599628860": {
        "extra": {},
        "level": 1,
        "number": 99,
        "nxtlvl": 200,
        "ranking": 0,
        "xp": 0,
        "xpcooldown": 0
    },
    "976224666467303466": {
        "extra": {},
        "level": 1,
        "number": 30,
        "nxtlvl": 200,
        "ranking": 0,
        "xp": 0,
        "xpcooldown": 0
    },
    "977606788738326569": {
        "extra": {},
        "level": 1,
        "number": 119,
        "nxtlvl": 200,
        "ranking": 0,
        "xp": 0,
        "xpcooldown": 0
    },
    "987026194300022895": {
        "extra": {},
        "level": 1,
        "number": 56,
        "nxtlvl": 200,
        "ranking": 0,
        "xp": 0,
        "xpcooldown": 0
    },
    "990015857067450438": {
        "extra": {},
        "level": 1,
        "number": 70,
        "nxtlvl": 200,
        "ranking": 0,
        "xp": 0,
        "xpcooldown": 0
    },
    "991498875179384872": {
        "extra": {},
        "level": 1,
        "number": 25,
        "nxtlvl": 200,
        "ranking": 0,
        "xp": 0,
        "xpcooldown": 0
    }
}